ckgen/__init__.py
ckgen/__main__.py
ckgen/atm.py
ckgen/main.py
ckgen/mpasocn.py
ckgen/utils.py
ckgen-0.1.2.dist-info/LICENSE
ckgen-0.1.2.dist-info/METADATA
ckgen-0.1.2.dist-info/WHEEL
ckgen-0.1.2.dist-info/entry_points.txt
ckgen-0.1.2.dist-info/top_level.txt
ckgen-0.1.2.dist-info/RECORD
