Metadata-Version: 2.1
Name: ckgen
Version: 0.1.2
Summary: Microapp CESM Fortran Kernel Generator
Author: Youngsung Kim
Author-email: youngsung.kim.act2@gmail.com
Project-URL: Bug Reports, https://github.com/grnydawn/ckgen/issues
Project-URL: Source, https://github.com/grnydawn/ckgen
Keywords: microapp fortlab ckgen
Classifier: Development Status :: 3 - Alpha
Classifier: Intended Audience :: Science/Research
Classifier: Topic :: Scientific/Engineering
Classifier: License :: OSI Approved :: MIT License
Classifier: Programming Language :: Python :: 3
Classifier: Programming Language :: Python :: 3.5
Classifier: Programming Language :: Python :: 3.6
Classifier: Programming Language :: Python :: 3.7
Classifier: Programming Language :: Python :: 3.8
License-File: LICENSE
Requires-Dist: fortlab>=1.1.5
